webserver/Liscence.md
webserver/README.md
webserver/__init__.py
webserver/__main__.py
webserver/main.py
webserver/php-cli-server.ini
webserver/settings.json
sachin_webserver-2.0.6.dist-info/METADATA
sachin_webserver-2.0.6.dist-info/WHEEL
sachin_webserver-2.0.6.dist-info/entry_points.txt
sachin_webserver-2.0.6.dist-info/top_level.txt
sachin_webserver-2.0.6.dist-info/RECORD
